git_commit_chart/__init__.py
git_commit_chart/app.py
git_commit_chart/static/favicon.js
git_commit_chart/static/style.css
git_commit_chart/static/theme.js
git_commit_chart/static/favicon/favicon-dark.svg
git_commit_chart/static/favicon/favicon-light.svg
git_commit_chart/static/favicon/favicon.ico
git_commit_chart/templates/by_user.html
git_commit_chart/templates/index.html
git_commit_chart-0.1.4.dist-info/LICENSE
git_commit_chart-0.1.4.dist-info/METADATA
git_commit_chart-0.1.4.dist-info/WHEEL
git_commit_chart-0.1.4.dist-info/entry_points.txt
git_commit_chart-0.1.4.dist-info/top_level.txt
git_commit_chart-0.1.4.dist-info/RECORD
